encexp/__init__.py
encexp/build_encexp.py
encexp/build_voc.py
encexp/download.py
encexp/text_repr.py
encexp/utils.py
encexp/data/emojis.json.gz
encexp/tests/__init__.py
encexp/tests/test_build_encexp.py
encexp/tests/test_build_voc.py
encexp/tests/test_download.py
encexp/tests/test_text_repr.py
encexp/tests/test_utils.py
encexp-0.1.9.dist-info/licenses/LICENSE
encexp-0.1.9.dist-info/METADATA
encexp-0.1.9.dist-info/WHEEL
encexp-0.1.9.dist-info/top_level.txt
encexp-0.1.9.dist-info/RECORD
