Metadata-Version: 2.4
Name: EncExp
Version: 0.1.9
Summary: Set of tools to create and use explainable embeddings.
Author: Eric S. Tellez, Mario Graff, Daniela Moctezuma
Maintainer-email: Mario Graff <mgraffg@ieee.org>
Project-URL: Repository, https://github.com/INGEOTEC/EncExp
Project-URL: Issues, https://github.com/INGEOTEC/EncExp/issues
Classifier: Development Status :: 3 - Alpha
Classifier: Environment :: Console
Classifier: Intended Audience :: Science/Research
Classifier: License :: OSI Approved :: Apache Software License
Classifier: Natural Language :: English
Classifier: Operating System :: Microsoft :: Windows
Classifier: Operating System :: MacOS :: MacOS X
Classifier: Operating System :: POSIX :: Linux
Classifier: Programming Language :: Python :: 3
Classifier: Topic :: Scientific/Engineering :: Artificial Intelligence
License-File: LICENSE
Requires-Dist: numpy
Requires-Dist: scikit-learn>=1.3.0
Requires-Dist: microtc
Dynamic: license-file
